memorylab/__init__.py
memorylab-0.0.1.dist-info/METADATA
memorylab-0.0.1.dist-info/WHEEL
memorylab-0.0.1.dist-info/top_level.txt
memorylab-0.0.1.dist-info/RECORD
