Metadata-Version: 2.2
Name: memorylab
Version: 0.0.1
Summary: MemoryLab SDK
Author-email: Devis Lucato <dluc@users.noreply.github.com>
